CHANGES.txt
MANIFEST.in
README.txt
setup.py
docs/LICENSE.ZPL
src/five/__init__.py
src/five.z2monitor.egg-info/PKG-INFO
src/five.z2monitor.egg-info/SOURCES.txt
src/five.z2monitor.egg-info/dependency_links.txt
src/five.z2monitor.egg-info/entry_points.txt
src/five.z2monitor.egg-info/namespace_packages.txt
src/five.z2monitor.egg-info/not-zip-safe
src/five.z2monitor.egg-info/requires.txt
src/five.z2monitor.egg-info/top_level.txt
src/five/z2monitor/__init__.py
src/five/z2monitor/configure.zcml
src/five/z2monitor/zope2instance.py