Metadata-Version: 1.1
Name: five.z2monitor
Version: 0.2
Summary: Enable zc.monitor with Zope 2
Home-page: http://pypi.python.org/pypi/five.monitor
Author: Zope Corporation and contributors
Author-email: zope-dev@zope.org
License: ZPL
Keywords: Zope zc.monitor monitoring
Platform: UNKNOWN
Classifier: Programming Language :: Python
Classifier: License :: OSI Approved :: Zope Public License
Classifier: Programming Language :: Python
Classifier: Topic :: System :: Monitoring
